trixs/__init__.py
trixs/spectra/__init__.py
trixs/spectra/core.py
trixs/spectra/spectrum_compare.py
trixs/spectra/spectrum_featurize.py
trixs/spectra/spectrum_io.py
trixs/spectra/spectrum_normalize.py
trixs/spectra/util.py
trixs/test/__init__.py
trixs/test/test_bechmarks.py
trixs/test/test_ml_benchmarks.py
trixs/test/test_spectrum_analyze.py
trixs/test/test_spectrum_compare.py
trixs/test/test_spectrum_core.py
trixs/test/test_spectrum_featurize.py
trixs/test/test_spectrum_io.py
trixs/test/test_spectrum_normalize.py
trixs-2020.7.8.dist-info/LICENSE
trixs-2020.7.8.dist-info/METADATA
trixs-2020.7.8.dist-info/WHEEL
trixs-2020.7.8.dist-info/entry_points.txt
trixs-2020.7.8.dist-info/top_level.txt
trixs-2020.7.8.dist-info/RECORD
