Metadata-Version: 2.1
Name: trixs
Version: 2020.7.8
Summary: Data analysis and machine learning for X-ray spectroscopy
Home-page: https://github.com/TRI-AMDD/trixs
Author: AMDD - Toyota Research Institute
Author-email: linda.hung@tri.global
Maintainer: Linda Hung
Maintainer-email: linda.hung@tri.global
License: Apache
Keywords: materials,chemistry,science,x-ray,spectroscopy,xanes,machine learning,AI,artificial intelligence
Platform: UNKNOWN
Classifier: Programming Language :: Python :: 3
Classifier: License :: OSI Approved :: Apache Software License
Classifier: Operating System :: OS Independent
Requires-Dist: scikit-learn (==0.23.1)
Requires-Dist: pymatgen
Requires-Dist: imbalanced-learn
Requires-Dist: tqdm
Requires-Dist: matplotlib
Requires-Dist: scipy
Requires-Dist: numpy
Provides-Extra: dev
Requires-Dist: pytest ; extra == 'dev'
Requires-Dist: ipywidgets ; extra == 'dev'
Requires-Dist: jupyterlab ; extra == 'dev'
Requires-Dist: setuptools ; extra == 'dev'
Requires-Dist: wheel ; extra == 'dev'
Requires-Dist: twine ; extra == 'dev'
Provides-Extra: tests
Requires-Dist: pytest ; extra == 'tests'
Requires-Dist: pytest-cov ; extra == 'tests'
Requires-Dist: coveralls ; extra == 'tests'
Requires-Dist: memory-profiler ; extra == 'tests'
